mcp_texicode/__init__.py
mcp_texicode/server.py
mcp_texicode-0.1.0.dist-info/METADATA
mcp_texicode-0.1.0.dist-info/WHEEL
mcp_texicode-0.1.0.dist-info/entry_points.txt
mcp_texicode-0.1.0.dist-info/licenses/LICENSE
mcp_texicode-0.1.0.dist-info/RECORD
