Metadata-Version: 2.4
Name: mcp-texicode
Version: 0.1.0
Summary: MCP server wrapping TeXicode CLI for LaTeX-formatted terminal output
Author-email: Chris Mitchell <ccmitchellusa@users.noreply.github.com>
License: MIT
License-File: LICENSE
Keywords: latex,mcp,terminal,texicode,unicode
Classifier: Development Status :: 3 - Alpha
Classifier: Intended Audience :: Developers
Classifier: License :: OSI Approved :: MIT License
Classifier: Programming Language :: Python :: 3
Classifier: Programming Language :: Python :: 3.10
Classifier: Programming Language :: Python :: 3.11
Classifier: Programming Language :: Python :: 3.12
Requires-Python: >=3.11
Requires-Dist: chuk-mcp-server>=0.1.0
Requires-Dist: texicode>=0.1.0
Provides-Extra: dev
Requires-Dist: black>=23.0.0; extra == 'dev'
Requires-Dist: mypy>=1.0.0; extra == 'dev'
Requires-Dist: pytest-asyncio>=0.21.0; extra == 'dev'
Requires-Dist: pytest>=7.0.0; extra == 'dev'
Requires-Dist: ruff>=0.1.0; extra == 'dev'
